[
    {
        "Argentina": "2766890",
        "Australia": "7686850",
        "Brazil": "8511965",
        "Canada": "9976140",
        "China": "9596960",
        "France": "547030",
        "Germany": "357021",
        "India": "3287590",
        "Indonesia": "1919440",
        "Italy": "301230",
        "Japan": "377835",
        "Mexico": "1972550",
        "Russia": "17075200",
        "Saudi Arabia": "1960582",
        "South Africa": "1219912",
        "Republic of Korea": "98480",
        "Turkey": "780580",
        "United Kingdom": "244820",
        "USA": "9629091"
    },
    {
        "Argentina": "40.12",
        "Australia": "22.18",
        "Brazil": "194.95",
        "Canada": "34.08",
        "China": "1340.91",
        "France": "62.77",
        "Germany": "81.76",
        "India": "1190.52",
        "Indonesia": "237.64",
        "Italy": "60.34",
        "Japan": "128.05",
        "Mexico": "112.32",
        "Russia": "142.9",
        "Saudi Arabia": "27.56",
        "South Africa": "49.99",
        "Republic of Korea": "49.41",
        "Turkey": "73",
        "United Kingdom": "62.26",
        "USA": "309.73"
    },
    {
        "Argentina": "40.57",
        "Australia": "22.49",
        "Brazil": "196.66",
        "Canada": "34.44",
        "China": "1347.35",
        "France": "63.09",
        "Germany": "81.78",
        "India": "1206.92",
        "Indonesia": "241.03",
        "Italy": "60.63",
        "Japan": "127.9",
        "Mexico": "113.74",
        "Russia": "142.41",
        "Saudi Arabia": "28.37",
        "South Africa": "50.59",
        "Republic of Korea": "49.78",
        "Turkey": "73.95",
        "United Kingdom": "62.74",
        "USA": "311.94"
    },
    {
        "Argentina": "41.03",
        "Australia": "22.77",
        "Brazil": "198.36",
        "Canada": "34.83",
        "China": "1354.04",
        "France": "63.41",
        "Germany": "81.92",
        "India": "1223.17",
        "Indonesia": "244.47",
        "Italy": "60.82",
        "Japan": "127.61",
        "Mexico": "114.87",
        "Russia": "141.92",
        "Saudi Arabia": "28.99",
        "South Africa": "51.2",
        "Republic of Korea": "50.01",
        "Turkey": "74.89",
        "United Kingdom": "63.24",
        "USA": "314.18"
    },
    {
        "Argentina": "41.49",
        "Australia": "23.05",
        "Brazil": "199.88",
        "Canada": "35.21",
        "China": "1360.76",
        "France": "63.7",
        "Germany": "81.75",
        "India": "1239.26",
        "Indonesia": "247.95",
        "Italy": "61",
        "Japan": "127.34",
        "Mexico": "116.02",
        "Russia": "141.44",
        "Saudi Arabia": "26.93",
        "South Africa": "51.81",
        "Republic of Korea": "50.24",
        "Turkey": "75.81",
        "United Kingdom": "63.76",
        "USA": "316.85"
    },
    {
        "Argentina": "367.57",
        "Australia": "1247.11",
        "Brazil": "2142.93",
        "Canada": "1616.02",
        "China": "5930.39",
        "France": "2570.59",
        "Germany": "3312.19",
        "India": "1614.83",
        "Indonesia": "709.54",
        "Italy": "2059.19",
        "Japan": "5495.39",
        "Mexico": "1034.15",
        "Russia": "1525.35",
        "Saudi Arabia": "526.81",
        "South Africa": "363.2",
        "Republic of Korea": "1014.89",
        "Turkey": "731.29",
        "United Kingdom": "2267.48",
        "USA": "14498.93"
    },
    {
        "Argentina": "444.61",
        "Australia": "1490.52",
        "Brazil": "2492.91",
        "Canada": "1781.08",
        "China": "7321.99",
        "France": "2778.09",
        "Germany": "3607.36",
        "India": "1838.17",
        "Indonesia": "846.16",
        "Italy": "2196.33",
        "Japan": "5897.02",
        "Mexico": "1158.3",
        "Russia": "1899.06",
        "Saudi Arabia": "669.51",
        "South Africa": "402.25",
        "Republic of Korea": "1116.25",
        "Turkey": "774.34",
        "United Kingdom": "2431.53",
        "USA": "15075.68"
    },
    {
        "Argentina": "474.95",
        "Australia": "1541.8",
        "Brazil": "2395.97",
        "Canada": "1819.08",
        "China": "8227.04",
        "France": "2608.7",
        "Germany": "3400.58",
        "India": "1824.83",
        "Indonesia": "878.2",
        "Italy": "2014.08",
        "Japan": "5963.97",
        "Mexico": "1177.12",
        "Russia": "2021.96",
        "Saudi Arabia": "727.31",
        "South Africa": "384.32",
        "Republic of Korea": "1155.87",
        "Turkey": "794.47",
        "United Kingdom": "2440.51",
        "USA": "15684.75"
    },
    {
        "Argentina": "498.7",
        "Australia": "1589.12",
        "Brazil": "2456.66",
        "Canada": "1843.75",
        "China": "9020.31",
        "France": "2739.27",
        "Germany": "3597.97",
        "India": "1972.84",
        "Indonesia": "946.39",
        "Italy": "2076.01",
        "Japan": "5149.9",
        "Mexico": "1274.97",
        "Russia": "2213.57",
        "Saudi Arabia": "745.62",
        "South Africa": "375.99",
        "Republic of Korea": "1258.59",
        "Turkey": "851.82",
        "United Kingdom": "2422.92",
        "USA": "16237.75"
    },
    {
        "Argentina": "9162.3",
        "Australia": "56219.82",
        "Brazil": "10992.38",
        "Canada": "47424.5",
        "China": "4422.66",
        "France": "40955.56",
        "Germany": "40512.53",
        "India": "1356.41",
        "Indonesia": "2985.77",
        "Italy": "34126.21",
        "Japan": "42916.74",
        "Mexico": "9207.36",
        "Russia": "10674.27",
        "Saudi Arabia": "19112.99",
        "South Africa": "7265.27",
        "Republic of Korea": "20540.18",
        "Turkey": "10017.3",
        "United Kingdom": "36418.42",
        "USA": "46811.06"
    },
    {
        "Argentina": "10959.08",
        "Australia": "66288.7",
        "Brazil": "12676.55",
        "Canada": "51716.26",
        "China": "5434.36",
        "France": "44034.38",
        "Germany": "44110.99",
        "India": "1523.03",
        "Indonesia": "3510.59",
        "Italy": "36227.33",
        "Japan": "46108",
        "Mexico": "10184.24",
        "Russia": "13335.01",
        "Saudi Arabia": "23599.11",
        "South Africa": "7951.14",
        "Republic of Korea": "22424.06",
        "Turkey": "10471.07",
        "United Kingdom": "38758.58",
        "USA": "48328.25"
    },
    {
        "Argentina": "11576.21",
        "Australia": "67722.59",
        "Brazil": "12078.83",
        "Canada": "52231.86",
        "China": "6075.92",
        "France": "41140.71",
        "Germany": "41512.75",
        "India": "1491.89",
        "Indonesia": "3592.29",
        "Italy": "33115.03",
        "Japan": "46735.72",
        "Mexico": "10247.18",
        "Russia": "14246.76",
        "Saudi Arabia": "25084.61",
        "South Africa": "7506.58",
        "Republic of Korea": "23112.93",
        "Turkey": "10609.18",
        "United Kingdom": "38588.81",
        "USA": "49922.11"
    },
    {
        "Argentina": "12019.18",
        "Australia": "68939.33",
        "Brazil": "12290.64",
        "Canada": "52364.36",
        "China": "6628.86",
        "France": "42999.97",
        "Germany": "44010.37",
        "India": "1591.95",
        "Indonesia": "3816.8",
        "Italy": "34034.39",
        "Japan": "40441.75",
        "Mexico": "10989.1",
        "Russia": "15650.36",
        "Saudi Arabia": "25162.54",
        "South Africa": "7256.98",
        "Republic of Korea": "25050.68",
        "Turkey": "11236.06",
        "United Kingdom": "38001.69",
        "USA": "51248.21"
    },
    {
        "Argentina": "644.35",
        "Australia": "880.09",
        "Brazil": "2186.54",
        "Canada": "1370.64",
        "China": "10128.4",
        "France": "2131.48",
        "Germany": "2957.38",
        "India": "4021.77",
        "Indonesia": "1034.65",
        "Italy": "1799.17",
        "Japan": "4389.48",
        "Mexico": "1566.31",
        "Russia": "2241.7",
        "Saudi Arabia": "619.83",
        "South Africa": "528.04",
        "Republic of Korea": "1468.33",
        "Turkey": "970.5",
        "United Kingdom": "2223.25",
        "USA": "14498.93"
    },
    {
        "Argentina": "716.45",
        "Australia": "920.75",
        "Brazil": "2294.18",
        "Canada": "1435.78",
        "China": "11305.77",
        "France": "2213.78",
        "Germany": "3113.93",
        "India": "4425.64",
        "Indonesia": "1125.29",
        "Italy": "1844.39",
        "Japan": "4457.56",
        "Mexico": "1662.36",
        "Russia": "2387.93",
        "Saudi Arabia": "656.23",
        "South Africa": "557.94",
        "Republic of Korea": "1554.12",
        "Turkey": "1075.47",
        "United Kingdom": "2291.43",
        "USA": "15075.68"
    },
    {
        "Argentina": "743.12",
        "Australia": "970.76",
        "Brazil": "2355.59",
        "Canada": "1488.31",
        "China": "12405.67",
        "France": "2254.07",
        "Germany": "3197.07",
        "India": "4684.37",
        "Indonesia": "1216.74",
        "Italy": "1832.92",
        "Japan": "4627.89",
        "Mexico": "1758.9",
        "Russia": "2513.3",
        "Saudi Arabia": "694.01",
        "South Africa": "582.39",
        "Republic of Korea": "1613.92",
        "Turkey": "1123.38",
        "United Kingdom": "2336.3",
        "USA": "15684.75"
    },
    {
        "Argentina": "776.28",
        "Australia": "1015.94",
        "Brazil": "2466.57",
        "Canada": "1534.94",
        "China": "13623.26",
        "France": "2289.92",
        "Germany": "3269.56",
        "India": "5031.68",
        "Indonesia": "1314.66",
        "Italy": "1835.66",
        "Japan": "4778.52",
        "Mexico": "1848.42",
        "Russia": "2640.74",
        "Saudi Arabia": "735.82",
        "South Africa": "608.8",
        "Republic of Korea": "1687.14",
        "Turkey": "1181.01",
        "United Kingdom": "2391.04",
        "USA": "16237.75"
    }
]